README.txt
setup.cfg
setup.py
docs/HISTORY.txt
docs/INSTALL.txt
docs/LICENSE.GPL
docs/LICENSE.txt
ripe/__init__.py
ripe.tinyurl.egg-info/PKG-INFO
ripe.tinyurl.egg-info/SOURCES.txt
ripe.tinyurl.egg-info/dependency_links.txt
ripe.tinyurl.egg-info/entry_points.txt
ripe.tinyurl.egg-info/namespace_packages.txt
ripe.tinyurl.egg-info/not-zip-safe
ripe.tinyurl.egg-info/paster_plugins.txt
ripe.tinyurl.egg-info/requires.txt
ripe.tinyurl.egg-info/top_level.txt
ripe/tinyurl/README.txt
ripe/tinyurl/__init__.py
ripe/tinyurl/configure.zcml
ripe/tinyurl/profiles.zcml
ripe/tinyurl/testing.py
ripe/tinyurl/version.txt
ripe/tinyurl/browser/__init__.py
ripe/tinyurl/browser/configure.zcml
ripe/tinyurl/browser/tinyurl.py
ripe/tinyurl/browser/javascripts/ripetinyurl.js
ripe/tinyurl/browser/stylesheets/ripetinyurl.css
ripe/tinyurl/browser/templates/tinyurl.pt
ripe/tinyurl/profiles/default/cssregistry.xml
ripe/tinyurl/profiles/default/jsregistry.xml
ripe/tinyurl/profiles/default/metadata.xml
ripe/tinyurl/tests/RipeTinyURL.txt
ripe/tinyurl/tests/__init__.py
ripe/tinyurl/tests/test_doctest.py
ripe/tinyurl/tests/test_unittest.py