Metadata-Version: 1.0
Name: ripe.tinyurl
Version: 1.1rc3
Summary: Short URL app for Plone
Home-page: http://svn.plone.org/svn/collective/
Author: Adam Castle
Author-email: acastle@ripe.net
License: GPL
Keywords: tinyurl
Platform: UNKNOWN
Classifier: Framework :: Plone
Classifier: Programming Language :: Python
